SolarWattEnergyManagerAPI/SolarWatt.py
SolarWattEnergyManagerAPI/__init__.py
SolarWattEnergyManagerAPI/__main__.py
SolarWattEnergyManagerAPI/units.py
SolarWattEnergyManagerAPI-0.5.4.dist-info/LICENSE.txt
SolarWattEnergyManagerAPI-0.5.4.dist-info/METADATA
SolarWattEnergyManagerAPI-0.5.4.dist-info/WHEEL
SolarWattEnergyManagerAPI-0.5.4.dist-info/top_level.txt
SolarWattEnergyManagerAPI-0.5.4.dist-info/RECORD
