Metadata-Version: 2.1
Name: SolarWattEnergyManagerAPI
Version: 0.5.4
Summary: API wrapper for solar watt energy manager
Home-page: https://github.com/SebastianWallat/SolarWattEnergyManagerAPI
Download-URL: https://github.com/SebastianWallat/SolarWattEnergyManagerAPI/archive/v_054.tar.gz
Author: Sebastian Wallat
Author-email: wallatsebastian@gmail.com
License: MIT
Keywords: IOT,Solar,Local
Classifier: Development Status :: 3 - Alpha
Classifier: Intended Audience :: Developers
Classifier: Topic :: Software Development :: Build Tools
Classifier: License :: OSI Approved :: MIT License
Classifier: Programming Language :: Python :: 3
Classifier: Programming Language :: Python :: 3.4
Classifier: Programming Language :: Python :: 3.5
Classifier: Programming Language :: Python :: 3.6
Classifier: Programming Language :: Python :: 3.7
License-File: LICENSE.txt
Requires-Dist: requests
